erre2/__init__.py
erre2/__main__.py
erre2/authentication.py
erre2/backend_tests.py
erre2/database/__init__.py
erre2/database/crud.py
erre2/database/db.py
erre2/database/models.py
erre2/database/schemas.py
erre2/dependencies.py
erre2/Files/pepperoni_secret.md
erre2/integrations.py
erre2/routers/__init__.py
erre2/routers/course.py
erre2/routers/server.py
erre2/routers/summary.py
erre2/routers/users.py
erre2-2.0.5.dist-info/WHEEL
erre2-2.0.5.dist-info/METADATA
erre2-2.0.5.dist-info/RECORD
