Metadata-Version: 2.1
Name: erre2
Version: 2.0.5
Summary: A new and improved version of Erre2.
Author: Lorenzo Balugani
Author-email: lorenzo.balugani@gmail.com
Requires-Python: >=3.8.5,<4.0.0
Classifier: Programming Language :: Python :: 3
Classifier: Programming Language :: Python :: 3.10
Classifier: Programming Language :: Python :: 3.9
Requires-Dist: SQLAlchemy (>=1.4.19,<2.0.0)
Requires-Dist: aiofiles (>=0.7.0,<0.8.0)
Requires-Dist: bcrypt (>=3.2.0,<4.0.0)
Requires-Dist: fastapi (>=0.65.2,<0.66.0)
Requires-Dist: passlib[bcrypt] (>=1.7.4,<2.0.0)
Requires-Dist: psycopg2 (>=2.9.1,<3.0.0)
Requires-Dist: pytest (>=6.2.5,<7.0.0)
Requires-Dist: python-jose[cryptography] (>=3.3.0,<4.0.0)
Requires-Dist: python-multipart (>=0.0.5,<0.0.6)
Requires-Dist: requests (>=2.26.0,<3.0.0)
Requires-Dist: uvicorn[standard] (>=0.14.0,<0.15.0)
